Workbook

Sheet Datos
A1: Fecha | B1: Vendedor | C1: Cliente | D1: Zona | E1: Producto | F1: Categoría | G1: Unidades | H1: Precio | I1: Costo unitario | J1: Importe
A2: 46307 | B2: Luis | C2: Fénix Ltda. | D2: Norte | E2: Licencia anual | F2: Software | G2: 1 | H2: 429.21 | I2: 291.59 | J2: 429.21
A3: 46304 | B3: Jorge | C3: Ola S.A. | D3: Norte | E3: Licencia anual | F3: Software | G3: 1 | H3: 405.98 | I3: 266.41 | J3: 405.98
A4: 46300 | B4: Jorge | C4: Lago Import | D4: Centro | E4: Capacitación | F4: Formación | G4: 1 | H4: 323.72 | I4: 226.34 | J4: 323.72
A5: 46297 | B5: Luis | C5: Huaca Comercial | D5: Sur | E5: Consultoría (hora) | F5: Servicios | G5: 1 | H5: 88.58 | I5: 65.19 | J5: 88.58
A6: 46317 | B6: Jorge | C6: Delta Comercial | D6: Centro | E6: Soporte mensual | F6: Servicios | G6: 1 | H6: 250.68 | I6: 181.21 | J6: 250.68
A7: 46317 | B7: Luis | C7: Mistura Foods | D7: Centro | E7: Soporte mensual | F7: Servicios | G7: 1 | H7: 225.93 | I7: 137.62 | J7: 225.93
A8: 46310 | B8: Ana | C8: Jade Foods | D8: Centro | E8: Soporte mensual | F8: Servicios | G8: 1 | H8: 274.47 | I8: 182.13 | J8: 274.47
A9: 46315 | B9: Luis | C9: Lago S.A.C. | D9: Centro | E9: Licencia anual | F9: Software | G9: 1 | H9: 492.42 | I9: 335.3 | J9: 492.42
A10: 46298 | B10: Jorge | C10: Huaca Group | D10: Norte | E10: Soporte mensual | F10: Servicios | G10: 1 | H10: 252.76 | I10: 170.89 | J10: 252.76
A11: 46315 | B11: Jorge | C11: Puna Servicios | D11: Norte | E11: Licencia anual | F11: Software | G11: 1 | H11: 465.13 | I11: 311.84 | J11: 465.13
A12: 46302 | B12: Carla | C12: Ícaro Servicios | D12: Norte | E12: Soporte mensual | F12: Servicios | G12: 1 | H12: 257.04 | I12: 157.41 | J12: 257.04
A13: 46308 | B13: Carla | C13: Fénix Servicios | D13: Centro | E13: Consultoría (hora) | F13: Servicios | G13: 1 | H13: 103.38 | I13: 75.46 | J13: 103.38
... A481: 46378 | B481: Carla | C481: Ícaro S.A.C. | D481: Norte | E481: Licencia anual | F481: Software | G481: 1 | H481: 418.36 | I481: 309.62 | J481: 418.36

Sheet Dashboard
A1: Dashboard de ventas Q4 2026
A2: Fuente: ventas-q4.xlsx (hoja Datos). Todo se recalcula con fórmulas.
A4: 1. Ingresos por mes | D4: 2. Margen bruto | G4: 3. Clientes | Q4: Auxiliar: clientes
A5: Mes | B5: Ingresos | D5: Concepto | E5: Valor | G5: Indicador | H5: Valor | Q5: Cliente | R5: Compras | S5: Ingresos
A6: Octubre | B6: =SUMIFS(Datos!$J$2:$J$481,Datos!$A$2:$A$481,">="&DATE(2026,10,1),Datos!$A$2:$A$481,"<"&DATE(2026,11,1)) | D6: Ingresos | E6: =SUM(Datos!$J$2:$J$481) | G6: Clientes activos | H6: =SUMPRODUCT((Datos!$C$2:$C$481<>"")/COUNTIF(Datos!$C$2:$C$481,Datos!$C$2:$C$481&"")) | Q6: Andes Comercial | R6: =COUNTIF(Datos!$C$2:$C$481,Q6) | S6: =SUMIFS(Datos!$J$2:$J$481,Datos!$C$2:$C$481,Q6)
A7: Noviembre | B7: =SUMIFS(Datos!$J$2:$J$481,Datos!$A$2:$A$481,">="&DATE(2026,11,1),Datos!$A$2:$A$481,"<"&DATE(2026,12,1)) | D7: Costo | E7: =SUMPRODUCT(Datos!$G$2:$G$481,Datos!$I$2:$I$481) | G7: Compraron una sola vez | H7: =COUNTIF($R$6:$R$219,1) | Q7: Andes Foods | R7: =COUNTIF(Datos!$C$2:$C$481,Q7) | S7: =SUMIFS(Datos!$J$2:$J$481,Datos!$C$2:$C$481,Q7)
A8: Diciembre | B8: =SUMIFS(Datos!$J$2:$J$481,Datos!$A$2:$A$481,">="&DATE(2026,12,1),Datos!$A$2:$A$481,"<"&DATE(2027,1,1)) | D8: Margen bruto | E8: =E6-E7 | G8: % una sola compra | H8: =IF(H6=0,0,H7/H6) | Q8: Andes Group | R8: =COUNTIF(Datos!$C$2:$C$481,Q8) | S8: =SUMIFS(Datos!$J$2:$J$481,Datos!$C$2:$C$481,Q8)
A9: Total | B9: =SUM(B6:B8) | D9: Margen bruto % | E9: =IF(E6=0,0,(E6-E7)/E6) | G9: % recurrentes | H9: =1-H8 | Q9: Andes Logística | R9: =COUNTIF(Datos!$C$2:$C$481,Q9) | S9: =SUMIFS(Datos!$J$2:$J$481,Datos!$C$2:$C$481,Q9)
A10: Var. último vs primer mes | B10: =IF(B6=0,0,(B8-B6)/B6) | Q10: Andes Ltda. | R10: =COUNTIF(Datos!$C$2:$C$481,Q10) | S10: =SUMIFS(Datos!$J$2:$J$481,Datos!$C$2:$C$481,Q10)
Q11: Andes Retail | R11: =COUNTIF(Datos!$C$2:$C$481,Q11) | S11: =SUMIFS(Datos!$J$2:$J$481,Datos!$C$2:$C$481,Q11)
A12: 4. Ingresos por región y categoría (región = columna "Zona") | Q12: Andes S.A. | R12: =COUNTIF(Datos!$C$2:$C$481,Q12) | S12: =SUMIFS(Datos!$J$2:$J$481,Datos!$C$2:$C$481,Q12)
A13: Zona | B13: Formación | C13: Servicios | D13: Software | E13: Total | Q13: Andes S.A.C. | R13: =COUNTIF(Datos!$C$2:$C$481,Q13) | S13: =SUMIFS(Datos!$J$2:$J$481,Datos!$C$2:$C$481,Q13)
A14: Centro | B14: =SUMIFS(Datos!$J$2:$J$481,Datos!$D$2:$D$481,$A14,Datos!$F$2:$F$481,B$13) | C14: =SUMIFS(Datos!$J$2:$J$481,Datos!$D$2:$D$481,$A14,Datos!$F$2:$F$481,C$13) | D14: =SUMIFS(Datos!$J$2:$J$481,Datos!$D$2:$D$481,$A14,Datos!$F$2:$F$481,D$13) | E14: =SUM(B14:D14) | Q14: Andes Servicios | R14: =COUNTIF(Datos!$C$2:$C$481,Q14) | S14: =SUMIFS(Datos!$J$2:$J$481,Datos!$C$2:$C$481,Q14)
A15: Norte | B15: =SUMIFS(Datos!$J$2:$J$481,Datos!$D$2:$D$481,$A15,Datos!$F$2:$F$481,B$13) | C15: =SUMIFS(Datos!$J$2:$J$481,Datos!$D$2:$D$481,$A15,Datos!$F$2:$F$481,C$13) | D15: =SUMIFS(Datos!$J$2:$J$481,Datos!$D$2:$D$481,$A15,Datos!$F$2:$F$481,D$13) | E15: =SUM(B15:D15) | Q15: Andes Tech | R15: =COUNTIF(Datos!$C$2:$C$481,Q15) | S15: =SUMIFS(Datos!$J$2:$J$481,Datos!$C$2:$C$481,Q15)
A16: Sur | B16: =SUMIFS(Datos!$J$2:$J$481,Datos!$D$2:$D$481,$A16,Datos!$F$2:$F$481,B$13) | C16: =SUMIFS(Datos!$J$2:$J$481,Datos!$D$2:$D$481,$A16,Datos!$F$2:$F$481,C$13) | D16: =SUMIFS(Datos!$J$2:$J$481,Datos!$D$2:$D$481,$A16,Datos!$F$2:$F$481,D$13) | E16: =SUM(B16:D16) | Q16: Bahía Comercial | R16: =COUNTIF(Datos!$C$2:$C$481,Q16) | S16: =SUMIFS(Datos!$J$2:$J$481,Datos!$C$2:$C$481,Q16)
A17: Total | B17: =SUM(B14:B16) | C17: =SUM(C14:C16) | D17: =SUM(D14:D16) | E17: =SUM(E14:E16) | Q17: Bahía Foods | R17: =COUNTIF(Datos!$C$2:$C$481,Q17) | S17: =SUMIFS(Datos!$J$2:$J$481,Datos!$C$2:$C$481,Q17)
Q18: Bahía Group | R18: =COUNTIF(Datos!$C$2:$C$481,Q18) | S18: =SUMIFS(Datos!$J$2:$J$481,Datos!$C$2:$C$481,Q18)
Q19: Bahía Import | R19: =COUNTIF(Datos!$C$2:$C$481,Q19) | S19: =SUMIFS(Datos!$J$2:$J$481,Datos!$C$2:$C$481,Q19)
A20: Ventas por zona (mayor a menor) | J20: Top 5 clientes por ingresos | Q20: Bahía Logística | R20: =COUNTIF(Datos!$C$2:$C$481,Q20) | S20: =SUMIFS(Datos!$J$2:$J$481,Datos!$C$2:$C$481,Q20)
A21: Zona | B21: Ingresos | J21: # | K21: Cliente | L21: Ingresos | Q21: Bahía Ltda. | R21: =COUNTIF(Datos!$C$2:$C$481,Q21) | S21: =SUMIFS(Datos!$J$2:$J$481,Datos!$C$2:$C$481,Q21)
A22: =INDEX($A$14:$A$16,MATCH(B22,$E$14:$E$16,0)) | B22: =LARGE($E$14:$E$16,1) | J22: 1 | K22: =INDEX($Q$6:$Q$219,MATCH(L22,$S$6:$S$219,0)) | L22: =LARGE($S$6:$S$219,1) | Q22: Bahía Retail | R22: =COUNTIF(Datos!$C$2:$C$481,Q22) | S22: =SUMIFS(Datos!$J$2:$J$481,Datos!$C$2:$C$481,Q22)
A23: =INDEX($A$14:$A$16,MATCH(B23,$E$14:$E$16,0)) | B23: =LARGE($E$14:$E$16,2) | J23: 2 | K23: =INDEX($Q$6:$Q$219,MATCH(L23,$S$6:$S$219,0)) | L23: =LARGE($S$6:$S$219,2) | Q23: Bahía S.A. | R23: =COUNTIF(Datos!$C$2:$C$481,Q23) | S23: =SUMIFS(Datos!$J$2:$J$481,Datos!$C$2:$C$481,Q23)
A24: =INDEX($A$14:$A$16,MATCH(B24,$E$14:$E$16,0)) | B24: =LARGE($E$14:$E$16,3) | J24: 3 | K24: =INDEX($Q$6:$Q$219,MATCH(L24,$S$6:$S$219,0)) | L24: =LARGE($S$6:$S$219,3) | Q24: Bahía S.A.C. | R24: =COUNTIF(Datos!$C$2:$C$481,Q24) | S24: =SUMIFS(Datos!$J$2:$J$481,Datos!$C$2:$C$481,Q24)
J25: 4 | K25: =INDEX($Q$6:$Q$219,MATCH(L25,$S$6:$S$219,0)) | L25: =LARGE($S$6:$S$219,4) | Q25: Bahía Servicios | R25: =COUNTIF(Datos!$C$2:$C$481,Q25) | S25: =SUMIFS(Datos!$J$2:$J$481,Datos!$C$2:$C$481,Q25)
J26: 5 | K26: =INDEX($Q$6:$Q$219,MATCH(L26,$S$6:$S$219,0)) | L26: =LARGE($S$6:$S$219,5) | Q26: Bahía Tech | R26: =COUNTIF(Datos!$C$2:$C$481,Q26) | S26: =SUMIFS(Datos!$J$2:$J$481,Datos!$C$2:$C$481,Q26)
Q27: Cóndor Comercial | R27: =COUNTIF(Datos!$C$2:$C$481,Q27) | S27: =SUMIFS(Datos!$J$2:$J$481,Datos!$C$2:$C$481,Q27)
Q28: Cóndor Foods | R28: =COUNTIF(Datos!$C$2:$C$481,Q28) | S28: =SUMIFS(Datos!$J$2:$J$481,Datos!$C$2:$C$481,Q28)
Q29: Cóndor Import | R29: =COUNTIF(Datos!$C$2:$C$481,Q29) | S29: =SUMIFS(Datos!$J$2:$J$481,Datos!$C$2:$C$481,Q29)
Q30: Cóndor Logística | R30: =COUNTIF(Datos!$C$2:$C$481,Q30) | S30: =SUMIFS(Datos!$J$2:$J$481,Datos!$C$2:$C$481,Q30)
Q31: Cóndor Ltda. | R31: =COUNTIF(Datos!$C$2:$C$481,Q31) | S31: =SUMIFS(Datos!$J$2:$J$481,Datos!$C$2:$C$481,Q31)
Q32: Cóndor Retail | R32: =COUNTIF(Datos!$C$2:$C$481,Q32) | S32: =SUMIFS(Datos!$J$2:$J$481,Datos!$C$2:$C$481,Q32)
Q33: Cóndor S.A. | R33: =COUNTIF(Datos!$C$2:$C$481,Q33) | S33: =SUMIFS(Datos!$J$2:$J$481,Datos!$C$2:$C$481,Q33)
Q34: Cóndor S.A.C. | R34: =COUNTIF(Datos!$C$2:$C$481,Q34) | S34: =SUMIFS(Datos!$J$2:$J$481,Datos!$C$2:$C$481,Q34)
Q35: Cóndor Servicios | R35: =COUNTIF(Datos!$C$2:$C$481,Q35) | S35: =SUMIFS(Datos!$J$2:$J$481,Datos!$C$2:$C$481,Q35)
Q36: Cóndor Tech | R36: =COUNTIF(Datos!$C$2:$C$481,Q36) | S36: =SUMIFS(Datos!$J$2:$J$481,Datos!$C$2:$C$481,Q36)
Q37: Delta Comercial | R37: =COUNTIF(Datos!$C$2:$C$481,Q37) | S37: =SUMIFS(Datos!$J$2:$J$481,Datos!$C$2:$C$481,Q37)
Q38: Delta Foods | R38: =COUNTIF(Datos!$C$2:$C$481,Q38) | S38: =SUMIFS(Datos!$J$2:$J$481,Datos!$C$2:$C$481,Q38)
... Q219: Ícaro Tech | R219: =COUNTIF(Datos!$C$2:$C$481,Q219) | S219: =SUMIFS(Datos!$J$2:$J$481,Datos!$C$2:$C$481,Q219)
